GPTPlugins4All/__init__.py
GPTPlugins4All/assistant.py
GPTPlugins4All/cli.py
GPTPlugins4All/config.py
GPTPlugins4All-1.0.62.dist-info/LICENSE
GPTPlugins4All-1.0.62.dist-info/METADATA
GPTPlugins4All-1.0.62.dist-info/WHEEL
GPTPlugins4All-1.0.62.dist-info/entry_points.txt
GPTPlugins4All-1.0.62.dist-info/top_level.txt
GPTPlugins4All-1.0.62.dist-info/RECORD
