Metadata-Version: 2.1
Name: GPTPlugins4All
Version: 1.0.62
Summary: GPT Plugins for 4all
Home-page: https://github.com/DataStreams-Solutions/GPTPlugins4All
Author-email: trevor@gptplugins4all.com
Project-URL: Bug Tracker, https://github.com/DataStreams-Solutions/GPTPlugins4All/issues
Project-URL: Documentation, https://github.com/DataStreams-Solutions/GPTPlugins4All#readme
Project-URL: Source Code, https://github.com/DataStreams-Solutions/GPTPlugins4All
Classifier: Programming Language :: Python :: 3
Classifier: License :: OSI Approved :: MIT License
Classifier: Operating System :: OS Independent
License-File: LICENSE
Requires-Dist: PyYAML
Requires-Dist: requests
Requires-Dist: openapi-spec-validator
Requires-Dist: bs4
Requires-Dist: googlesearch-python>=1.2.3
Requires-Dist: tiktoken
Provides-Extra: openai
Requires-Dist: openai; extra == "openai"
